[
  {
    "groupe": [
      "Leroy Emma",
      "Moreau Lucas",
      "Petit Chloé",
      "Faure Léa",
      "martin max"
    ],
    "score": 320
  },
  {
    "groupe": [
      "Roux Nathan",
      "Garnier Louis",
      "Blanc Manon",
      "Michel Mathis",
      "Fernandez Sarah"
    ],
    "score": 405
  },
  {
    "groupe": [
      "Garcia Enzo",
      "Perrin Louise",
      "Martinez Hugo",
      "Chevalier Clara",
      "Robin Inès"
    ],
    "score": 305
  },
  {
    "groupe": [
      "Henry Jules",
      "Lemoine Camille",
      "Dupuis Ethan",
      "Colin Noah",
      "Marchand Julia"
    ],
    "score": 325
  },
  {
    "groupe": [
      "Haifa Joe",
      "weinberg ben",
      "messi leo",
      "giami candice",
      "Gauthier Maxime"
    ],
    "score": 470
  }
]